comfy_env/__init__.py
comfy_env/cli.py
comfy_env/install.py
comfy_env/config/__init__.py
comfy_env/config/parser.py
comfy_env/config/types.py
comfy_env/detection/__init__.py
comfy_env/detection/cuda.py
comfy_env/detection/gpu.py
comfy_env/detection/platform.py
comfy_env/detection/runtime.py
comfy_env/environment/__init__.py
comfy_env/environment/cache.py
comfy_env/environment/libomp.py
comfy_env/environment/paths.py
comfy_env/environment/setup.py
comfy_env/isolation/__init__.py
comfy_env/isolation/tensor_utils.py
comfy_env/isolation/wrap.py
comfy_env/isolation/workers/__init__.py
comfy_env/isolation/workers/base.py
comfy_env/isolation/workers/subprocess.py
comfy_env/packages/__init__.py
comfy_env/packages/apt.py
comfy_env/packages/cuda_wheels.py
comfy_env/packages/node_dependencies.py
comfy_env/packages/pixi.py
comfy_env/packages/toml_generator.py
comfy_env/templates/comfy-env-instructions.txt
comfy_env/templates/comfy-env.toml
comfy_env-0.1.24.dist-info/METADATA
comfy_env-0.1.24.dist-info/WHEEL
comfy_env-0.1.24.dist-info/entry_points.txt
comfy_env-0.1.24.dist-info/licenses/LICENSE
comfy_env-0.1.24.dist-info/RECORD
