Metadata-Version: 2.4
Name: comfy-env
Version: 0.1.24
Summary: Environment management for ComfyUI custom nodes - CUDA wheel resolution and process isolation
Project-URL: Homepage, https://github.com/PozzettiAndrea/comfy-env
Project-URL: Repository, https://github.com/PozzettiAndrea/comfy-env
Project-URL: Issues, https://github.com/PozzettiAndrea/comfy-env/issues
Author: Andrea Pozzetti
License: MIT
License-File: LICENSE
Keywords: comfyui,cuda,environment,isolation,process,venv,wheels
Classifier: Development Status :: 3 - Alpha
Classifier: Intended Audience :: Developers
Classifier: License :: OSI Approved :: MIT License
Classifier: Programming Language :: Python :: 3.10
Classifier: Programming Language :: Python :: 3.11
Classifier: Programming Language :: Python :: 3.12
Classifier: Programming Language :: Python :: 3.13
Requires-Python: >=3.10
Requires-Dist: numpy
Requires-Dist: pip>=21.0
Requires-Dist: tomli-w>=1.0.0
Requires-Dist: tomli>=2.0.0
Requires-Dist: uv>=0.4.0
Provides-Extra: dev
Requires-Dist: mypy; extra == 'dev'
Requires-Dist: pytest; extra == 'dev'
Requires-Dist: ruff; extra == 'dev'
